medimagecleaner/__init__.py
medimagecleaner/audit_logger.py
medimagecleaner/batch_processor.py
medimagecleaner/cli.py
medimagecleaner/dicom_deidentifier.py
medimagecleaner/face_remover.py
medimagecleaner/format_converter.py
medimagecleaner/phi_detector.py
medimagecleaner/progress.py
medimagecleaner/risk_assessment.py
medimagecleaner/text_remover.py
medimagecleaner/validator.py
medimagecleaner-0.2.0.dist-info/licenses/LICENSE
medimagecleaner-0.2.0.dist-info/METADATA
medimagecleaner-0.2.0.dist-info/WHEEL
medimagecleaner-0.2.0.dist-info/entry_points.txt
medimagecleaner-0.2.0.dist-info/top_level.txt
medimagecleaner-0.2.0.dist-info/RECORD
