Metadata-Version: 2.4
Name: medimagecleaner
Version: 0.2.0
Summary: Comprehensive package for removing PHI from medical images
Home-page: https://github.com/akinboye/medimagecleaner
Author: Akinboye Yusuff
Author-email: Akinboye Yusuff <mailakinboye@gmail.com>
License: MIT
Project-URL: Homepage, https://github.com/akinboye/medimagecleaner
Project-URL: Documentation, https://github.com/akinboye/medimagecleaner#readme
Project-URL: Repository, https://github.com/akinboye/medimagecleaner
Project-URL: Issues, https://github.com/akinboye/medimagecleaner/issues
Project-URL: Author Website, https://akinboye.dev/
Keywords: medical imaging,dicom,deidentification,phi removal,hipaa,privacy
Classifier: Development Status :: 4 - Beta
Classifier: Intended Audience :: Healthcare Industry
Classifier: Intended Audience :: Science/Research
Classifier: Topic :: Scientific/Engineering :: Medical Science Apps.
Classifier: License :: OSI Approved :: MIT License
Classifier: Programming Language :: Python :: 3
Classifier: Programming Language :: Python :: 3.8
Classifier: Programming Language :: Python :: 3.9
Classifier: Programming Language :: Python :: 3.10
Classifier: Programming Language :: Python :: 3.11
Classifier: Programming Language :: Python :: 3.12
Requires-Python: >=3.8
License-File: LICENSE
Requires-Dist: pydicom>=2.3.0
Requires-Dist: numpy>=1.20.0
Requires-Dist: opencv-python>=4.5.0
Requires-Dist: Pillow>=9.0.0
Provides-Extra: ocr
Requires-Dist: pytesseract>=0.3.9; extra == "ocr"
Provides-Extra: dev
Requires-Dist: pytest>=7.0.0; extra == "dev"
Requires-Dist: black>=22.0.0; extra == "dev"
Requires-Dist: flake8>=4.0.0; extra == "dev"
Requires-Dist: mypy>=0.950; extra == "dev"
Provides-Extra: all
Requires-Dist: pytesseract>=0.3.9; extra == "all"
Dynamic: author
Dynamic: home-page
Dynamic: license-file
Dynamic: requires-python
